{
    "appKeys": {},
    "capabilities": [
        ""
    ],
    "companyName": "sadiklsd@gmail.com",
    "longName": "test1",
    "projectType": "pebblejs",
    "resources": {
        "media": [
            {
                "file": "images/menu_icon.png",
                "menuIcon": false,
                "name": "IMAGE_MENU_ICON",
                "type": "bitmap"
            },
            {
                "file": "images/logo_splash.png",
                "name": "IMAGE_LOGO_SPLASH",
                "type": "bitmap"
            },
            {
                "file": "images/tile_splash.png",
                "name": "IMAGE_TILE_SPLASH",
                "type": "bitmap"
            },
            {
                "file": "fonts/UbuntuMono-Regular.ttf",
                "name": "MONO_FONT_14",
                "type": "font"
            },
            {
                "file": "images/indicator_messages_new",
                "name": "IMAGES_INDICATOR_MESSAGES_NEW",
                "type": "bitmap"
            }
        ]
    },
    "sdkVersion": "3",
    "shortName": "test1",
    "uuid": "3f2b8463-3ded-4370-ab8f-fd3e47dd802a",
    "versionCode": 1,
    "versionLabel": "1.0",
    "watchapp": {
        "hiddenApp": false,
        "watchface": false
    }
}
